MANIFEST.in
README.md
setup.cfg
setup.py
binary_indexed_tree/__init__.py
binary_indexed_tree/bit.cpp
binary_indexed_tree/bit.py
binary_indexed_tree/bit_cpp_extension.pyi
bisect_decr/__init__.py
bisect_decr/bisect_decr.cpp
bisect_decr/bisect_decr_cpp.pyi
cpp_extension_hello/__init__.py
cpp_extension_hello/hello.cpp
cpp_extension_hello/hello_cpp_extension.pyi
data_structure_demos_hans.egg-info/PKG-INFO
data_structure_demos_hans.egg-info/SOURCES.txt
data_structure_demos_hans.egg-info/dependency_links.txt
data_structure_demos_hans.egg-info/top_level.txt
tests/test_bisect_decr.py
tests/test_bit_cpp.py
tests/test_bit_py.py
tests/test_hello_cpp_extension.py