Metadata-Version: 2.1
Name: data-structure-demos-hans
Version: 0.2.0
Summary: provide some data structures for competitive programming
Home-page: https://github.com/Hans774882968/data-structure-demos-hans
Author: hans
Author-email: 774882968@qq.com
License: MIT
